MANIFEST.in
README.md
TODO
musictoolbox.spec
mypy.ini
pyproject.toml
setup.cfg
tox.ini
lib/musictoolbox/__init__.py
lib/musictoolbox/cache.py
lib/musictoolbox/files.py
lib/musictoolbox/logging.py
lib/musictoolbox/py.typed
lib/musictoolbox/tagging.py
lib/musictoolbox/util.py
lib/musictoolbox.egg-info/PKG-INFO
lib/musictoolbox.egg-info/SOURCES.txt
lib/musictoolbox.egg-info/dependency_links.txt
lib/musictoolbox.egg-info/entry_points.txt
lib/musictoolbox.egg-info/requires.txt
lib/musictoolbox.egg-info/top_level.txt
lib/musictoolbox/cmd/__init__.py
lib/musictoolbox/cmd/cpm3u.py
lib/musictoolbox/cmd/detect.py
lib/musictoolbox/cmd/doreplaygain.py
lib/musictoolbox/cmd/fixplaylist.py
lib/musictoolbox/cmd/genplaylist.py
lib/musictoolbox/cmd/makealbumplaylist.py
lib/musictoolbox/cmd/removemusicbrainz.py
lib/musictoolbox/cmd/scanalbumartists.py
lib/musictoolbox/cmd/view.py
lib/musictoolbox/sync/__init__.py
lib/musictoolbox/sync/algo.py
lib/musictoolbox/sync/cli.py
lib/musictoolbox/sync/core.py
lib/musictoolbox/sync/interfaces.py
lib/musictoolbox/sync/test_algo.py
lib/musictoolbox/sync/test_core.py
lib/musictoolbox/transcoding/__init__.py
lib/musictoolbox/transcoding/cli.py
lib/musictoolbox/transcoding/config.py
lib/musictoolbox/transcoding/interfaces.py
lib/musictoolbox/transcoding/policies.py
lib/musictoolbox/transcoding/registry.py
lib/musictoolbox/transcoding/settings.py
lib/musictoolbox/transcoding/test_policies.py
lib/musictoolbox/transcoding/test_registry.py
lib/musictoolbox/transcoding/transcoder.py
lib/musictoolbox/transcoding/codecs/__init__.py
lib/musictoolbox/transcoding/codecs/base.py
lib/musictoolbox/transcoding/codecs/basic.py
lib/musictoolbox/transcoding/codecs/gstreamerffmpeg.py
lib/musictoolbox/transcoding/codecs/test_codecs.py