Metadata-Version: 2.1
Name: musictoolbox
Version: 0.0.83
Summary: Utilities to help you groom your music collection
Home-page: https://github.com/Rudd-O/musictoolbox
Author: Manuel Amador (Rudd-O)
Author-email: rudd-o@rudd-o.com
License: GPLv2
Keywords: mp3 ogg mkv transcoding aac mp4 video flv flac
Classifier: Development Status :: 4 - Beta
Classifier: Environment :: Console
Classifier: Intended Audience :: End Users/Desktop
Classifier: License :: OSI Approved :: GNU General Public License (GPL)
Classifier: Operating System :: POSIX :: Linux
Classifier: Programming Language :: Python :: 3 :: Only
Classifier: Topic :: Utilities
Requires-Dist: mutagen
Requires-Dist: networkx
Requires-Dist: pyxdg
Requires-Dist: psutil
Requires-Dist: PyYAML
Requires-Dist: packaging
Requires-Dist: rgain3
